[
  {
    "sentence": "Je _____ francais. (I speak French)",
    "hint": "I speak French"
  },
  {
    "sentence": "Il _____ beau aujourd'hui. (It is nice today)",
    "hint": "It is nice today"
  },
  {
    "sentence": "Nous _____ en France. (We live in France)",
    "hint": "We live in France"
  },
  {
    "sentence": "Elle _____ Marie. (Her name is Marie)",
    "hint": "Her name is Marie"
  },
  {
    "sentence": "J'ai _____ a la tete. (I have a headache)",
    "hint": "I have a headache"
  },
  {
    "sentence": "Ou _____ la gare ? (Where is the station?)",
    "hint": "Where is the station?"
  },
  {
    "sentence": "Je _____ un cafe. (I would like a coffee)",
    "hint": "I would like a coffee"
  },
  {
    "sentence": "Ils _____ etudiants. (They are students)",
    "hint": "They are students"
  },
  {
    "sentence": "Tu _____ quel age ? (How old are you?)",
    "hint": "How old are you?"
  },
  {
    "sentence": "Je me _____ a sept heures. (I wake up at 7)",
    "hint": "I wake up at 7"
  },
  {
    "sentence": "Il _____ du vent. (It is windy)",
    "hint": "It is windy"
  },
  {
    "sentence": "Nous _____ au cinema. (We go to the cinema)",
    "hint": "We go to the cinema"
  },
  {
    "sentence": "Je ne _____ pas. (I don't understand)",
    "hint": "I don't understand"
  },
  {
    "sentence": "C'est trop _____. (It's too expensive)",
    "hint": "It's too expensive"
  },
  {
    "sentence": "Je suis _____. (I am tired)",
    "hint": "I am tired"
  },
  {
    "sentence": "Vous _____ anglais ? (Do you speak English?)",
    "hint": "Do you speak English?"
  },
  {
    "sentence": "Il _____ huit heures. (It is eight o'clock)",
    "hint": "It is eight o'clock"
  },
  {
    "sentence": "J'_____ la musique. (I like music)",
    "hint": "I like music"
  },
  {
    "sentence": "Nous _____ trois enfants. (We have 3 children)",
    "hint": "We have 3 children"
  },
  {
    "sentence": "La pharmacie est _____ droite. (The pharmacy is on the right)",
    "hint": "The pharmacy is on the right"
  },
  {
    "sentence": "Je _____ du jogging le matin. (I jog in the morning)",
    "hint": "I jog in the morning"
  },
  {
    "sentence": "Le restaurant _____ a midi. (The restaurant opens at noon)",
    "hint": "The restaurant opens at noon"
  },
  {
    "sentence": "Ma soeur _____ plus jeune. (My sister is younger)",
    "hint": "My sister is younger"
  },
  {
    "sentence": "Ils _____ au restaurant. (They eat at the restaurant)",
    "hint": "They eat at the restaurant"
  },
  {
    "sentence": "Tu _____ libre ce soir ? (Are you free tonight?)",
    "hint": "Are you free tonight?"
  }
]